chatgpt_md_converter/__init__.py
chatgpt_md_converter/html_splitter.py
chatgpt_md_converter/html_to_markdown.py
chatgpt_md_converter/telegram_formatter.py
chatgpt_md_converter/html_markdown/escaping.py
chatgpt_md_converter/html_markdown/handlers.py
chatgpt_md_converter/html_markdown/renderer.py
chatgpt_md_converter/html_markdown/state.py
chatgpt_md_converter/html_markdown/tree.py
chatgpt_md_converter/telegram_markdown/__init__.py
chatgpt_md_converter/telegram_markdown/code_blocks.py
chatgpt_md_converter/telegram_markdown/inline.py
chatgpt_md_converter/telegram_markdown/postprocess.py
chatgpt_md_converter/telegram_markdown/preprocess.py
chatgpt_md_converter/telegram_markdown/renderer.py
chatgpt_md_converter-0.3.10.dist-info/licenses/LICENSE
chatgpt_md_converter-0.3.10.dist-info/METADATA
chatgpt_md_converter-0.3.10.dist-info/WHEEL
chatgpt_md_converter-0.3.10.dist-info/top_level.txt
chatgpt_md_converter-0.3.10.dist-info/RECORD
