Metadata-Version: 2.4
Name: chatgpt_md_converter
Version: 0.3.10
Summary: A package for converting markdown to HTML for chat Telegram bots
Home-page: https://github.com/botfather-dev/formatter-chatgpt-telegram
Author: Kostiantyn Kriuchkov
Author-email: latand666@gmail.com
Classifier: Programming Language :: Python :: 3
Classifier: License :: OSI Approved :: MIT License
Classifier: Operating System :: OS Independent
Requires-Python: >=3.8
License-File: LICENSE
Dynamic: author
Dynamic: author-email
Dynamic: classifier
Dynamic: description
Dynamic: description-content-type
Dynamic: home-page
Dynamic: license-file
Dynamic: requires-python
Dynamic: summary
